data/VCDs/import_vcd.sv
module import_vcd;

   reg clk1, clk2;
   reg A, B, C;
   reg [3:0] DATA_i;
   reg [3:0] DATA_o;


   initial begin
      clk1 = 'b0;
      clk2 = 'b0;

      B = 'bx;
      C = 'bx;
      DATA_i = 'hx;
      DATA_o = 'hx;
   end


   always begin
      #(10ns);
      clk1 = ~clk1;
   end

   always begin
      @(posedge clk1);
      clk2 = ~clk2;
   end

   initial begin
      A = 'bx;
      @(posedge clk1);
      #(2ns:2ns:4ns);
      A = 1;
      repeat(2)
	@(posedge clk1);
      #(2ns:2ns:4ns);
      A = 0;
      @(posedge clk1);
      #(3ns:3ns:4ns);
      A = 1;
      @(posedge clk1);
      #(4ns:4ns:6ns);
      A = 'bx;
   end // initial begin

   initial begin
      B = 'bx;
      @(posedge clk2);
      #(4ns:4ns:5ns);
      B = 0;
      @(posedge clk2);
      #(6ns:6ns:8ns);
      B = 1;
      @(posedge clk2);
      #(3ns:3ns:4ns);
      B = 'bz;
      @(posedge clk2);
      #(4ns:4ns:6ns);
      B = 0;
   end // initial begin

   initial begin
      C = 'bz;
      @(posedge clk2);
      #(2ns:2ns:5ns);
      C = 1;
      @(posedge clk2);
      #(5ns:5ns:7ns);
      C = 0;
      @(posedge clk2);
      #(3ns:3ns:4ns);
      C = 'bz;
      @(posedge clk2);
      #(4ns:4ns:6ns);
      C = 'bx;
   end // initial begin


   
   initial begin
      DATA_i = 'hx;
      @(posedge clk2);
      #(2ns:2ns:5ns);
      DATA_i = 'h0;
      @(posedge clk2);
      @(posedge clk2);
      #(5ns:5ns:7ns);
      DATA_i = 'hA;
      @(posedge clk2);
      @(posedge clk2);
      #(3ns:3ns:4ns);
      DATA_i = 'hz;
      @(posedge clk2);
      #(4ns:4ns:6ns);
      DATA_i = 'hx;
   end // initial begin

   
   initial begin
      DATA_o = 'hx;
      @(posedge clk1);
      #(2ns:2ns:6ns);
      DATA_o = 'h0;
      @(posedge clk1);
      @(posedge clk1);
      #(3ns:3ns:6ns);
      DATA_o = 'hA;
      @(posedge clk1);
      @(posedge clk1);
      #(3ns:3ns:5ns);
      DATA_o = 'hz;
      @(posedge clk1);
      #(4ns:4ns:6ns);
      DATA_o = 'hx;
   end // initial begin


endmodule // import_vcd

data/VCDs/import_vcd.max.vcd
$date
	Mon Aug 31 15:09:01 2026
$end
$version
	ModelSim Version 2020.1
$end
$timescale
	1ps
$end
$scope module import_vcd $end
$var reg 1 ! clk1 $end
$var reg 1 " clk2 $end
$var reg 1 # A $end
$var reg 1 $ B $end
$var reg 1 % C $end
$var reg 4 & DATA_i [3:0] $end
$var reg 4 ' DATA_o [3:0] $end
$upscope $end
$enddefinitions $end
#0
b0 !
b0 "
bx #
bx $
bz %
bx &
bx '
#10000
b1 !
b1 "
#14000
b1 #
#15000
b0 &
b1 %
b0 $
#16000
b0 '
#20000
b0 !
#30000
b1 !
b0 "
#40000
b0 !
#50000
b1 !
b1 "
#54000
b0 #
#56000
b1010 '
#57000
b0 %
#58000
b1 $
#60000
b0 !
#70000
b1 !
b0 "
#74000
b1 #
#80000
b0 !
#90000
b1 !
b1 "
#94000
bz $
bz %
#95000
bz '
#96000
bx #
#97000
b1010 &
#100000
b0 !
#110000
b1 !
b0 "
#116000
bx '
#120000
b0 !
#130000
b1 !
b1 "
#136000
bx %
b0 $
#140000
b0 !
#150000
b1 !
b0 "
#160000
b0 !
#170000
b1 !
b1 "
#174000
bz &
#180000
b0 !
#190000
b1 !
b0 "
#200000
b0 !
